filework/__init__.py
filework/filework.py
filework-1.1.2.dist-info/DESCRIPTION.rst
filework-1.1.2.dist-info/METADATA
filework-1.1.2.dist-info/RECORD
filework-1.1.2.dist-info/WHEEL
filework-1.1.2.dist-info/entry_points.txt
filework-1.1.2.dist-info/metadata.json
filework-1.1.2.dist-info/top_level.txt
