Metadata-Version: 2.0
Name: filework
Version: 1.1.2
Summary: A simple wrapper class for easy reading from/iterating through, writing, and appending to files.
Home-page: https://github.com/aescwork/filework
Author: aescwork
Author-email: aescwork@protonmail.com
License: MIT
Keywords: filework development files file read write delete append
Platform: UNKNOWN
Classifier: Development Status :: 5 - Production/Stable
Classifier: Intended Audience :: Developers
Classifier: Topic :: Software Development
Classifier: Topic :: System :: Filesystems
Classifier: License :: OSI Approved :: MIT License
Classifier: Programming Language :: Python :: 2.7
Classifier: Programming Language :: Python :: 3.5
